{
 "actions": [],
 "allow_rename": 1,
 "creation": "2025-12-20 14:18:50.536913",
 "doctype": "DocType",
 "engine": "InnoDB",
 "field_order": [
  "employee",
  "employee_name",
  "designation",
  "include"
 ],
 "fields": [
  {
   "fieldname": "employee",
   "fieldtype": "Link",
   "in_list_view": 1,
   "label": "Employee",
   "options": "Employee"
  },
  {
   "fieldname": "employee_name",
   "fieldtype": "Data",
   "in_list_view": 1,
   "label": "Employee Name"
  },
  {
   "fieldname": "designation",
   "fieldtype": "Link",
   "in_list_view": 1,
   "label": "Designation",
   "options": "Designation"
  },
  {
   "default": "0",
   "fieldname": "include",
   "fieldtype": "Check",
   "in_list_view": 1,
   "label": "Include"
  }
 ],
 "grid_page_length": 50,
 "index_web_pages_for_search": 1,
 "istable": 1,
 "links": [],
 "modified": "2025-12-20 14:21:33.260257",
 "modified_by": "Administrator",
 "module": "Security Agency",
 "name": "Bulk Guard Rotation Employee",
 "owner": "Administrator",
 "permissions": [],
 "row_format": "Dynamic",
 "sort_field": "modified",
 "sort_order": "DESC",
 "states": []
}